tests/__init__.py
tests/entity_factory_test.py
tests/entity_type_test.py
tests/event_factory_test.py
wikivents/__init__.py
wikivents/exc.py
wikivents/model_encoders.py
wikivents/models.py
wikivents/cache/__init__.py
wikivents/factories/__init__.py
wikivents/factories/wikimedia.py
wikivents/ontology/__init__.py
wikivents/ontology/exc.py
wikivents/ontology/wikidata.py
wikivents/resource/__init__.py
wikivents/resource/exc.py
wikivents/resource/wikipedia.py
wikivents-1.0.4.dist-info/AUTHORS
wikivents-1.0.4.dist-info/LICENSE
wikivents-1.0.4.dist-info/METADATA
wikivents-1.0.4.dist-info/WHEEL
wikivents-1.0.4.dist-info/top_level.txt
wikivents-1.0.4.dist-info/RECORD
