Metadata-Version: 2.1
Name: wikivents
Version: 1.0.4
Summary: A simple Python package to represent events from Wikipedia and Wikidata resources.
Home-page: https://gitlab.com/guilieb/wikivents
Author: Guillaume Bernard
Author-email: contact@guillaume-bernard.fr
License: GPLv3 License
Classifier: License :: OSI Approved :: GNU General Public License v3 or later (GPLv3+)
Classifier: Intended Audience :: Developers
Classifier: Intended Audience :: Education
Classifier: Topic :: Scientific/Engineering :: Information Analysis
Classifier: Operating System :: OS Independent
Classifier: Programming Language :: Python
Classifier: Programming Language :: Python :: 3.7
Classifier: Programming Language :: Python :: 3.8
License-File: LICENSE
License-File: AUTHORS
Requires-Dist: mwclient (==0.10.1)
Requires-Dist: SPARQLWrapper (==1.8.5)
Requires-Dist: Wikidata (==0.7.0)
Requires-Dist: dill
Requires-Dist: progress
